LICENSE
MANIFEST.in
README.md
setup.py
cmsplugin_flexiblevideo/__init__.py
cmsplugin_flexiblevideo/cms_plugins.py
cmsplugin_flexiblevideo/models.py
cmsplugin_flexiblevideo/tests.py
cmsplugin_flexiblevideo/views.py
cmsplugin_flexiblevideo.egg-info/PKG-INFO
cmsplugin_flexiblevideo.egg-info/SOURCES.txt
cmsplugin_flexiblevideo.egg-info/dependency_links.txt
cmsplugin_flexiblevideo.egg-info/requires.txt
cmsplugin_flexiblevideo.egg-info/top_level.txt
cmsplugin_flexiblevideo/migrations/0001_initial.py
cmsplugin_flexiblevideo/migrations/__init__.py
cmsplugin_flexiblevideo/templates/flexiblevideo/video.html