Metadata-Version: 1.0
Name: cmsplugin-flexiblevideo
Version: 0.0.5
Summary: Plugin for Django CMS that displays a video with flexible width.
Home-page: http://github.com/codemill/cmsplugin-flexiblevideo
Author: Ludvig Widman, CodeMill AB
Author-email: opensource@codemill.se
License: UNKNOWN
Platform: UNKNOWN
